ETH_GTD_cli/__init__.py
ETH_GTD_cli/auth.py
ETH_GTD_cli/consts.py
ETH_GTD_cli/helper.py
ETH_GTD_cli/main.py
eth_gtd_cli-0.0.109.dist-info/METADATA
eth_gtd_cli-0.0.109.dist-info/WHEEL
eth_gtd_cli-0.0.109.dist-info/entry_points.txt
eth_gtd_cli-0.0.109.dist-info/licenses/LICENSE
eth_gtd_cli-0.0.109.dist-info/RECORD
